[
  {
    "appid": 33230,
    "name": "Assassin's Creed II",
    "description": "Assassin's Creed II bypass for Ubisoft Connect DRM",
    "download_url": "https://drive.google.com/file/d/18BTyFkb4GmIwwT9Mc_wiQx2qToAeIQlN/view?usp=sharing",
    "file_id": "Z5bGkCeh",
    "size": 15728640,
    "version": "1.0",
    "updated_at": "2025-10-24",
    "category": "ubisoft",
    "drm_type": "Ubisoft Connect",
    "notes": "Extract to game folder. Launch via Steam or exe."
  },
  {
    "appid": 48190,
    "name": "Assassin's Creed Brotherhood",
    "description": "Assassin's Creed Brotherhood bypass for Ubisoft Connect",
    "download_url": "https://pixeldrain.com/api/file/YOUR_FILE_ID_HERE_2",
    "file_id": "YOUR_FILE_ID_HERE_2",
    "size": 12582912,
    "version": "1.0",
    "updated_at": "2025-01-15",
    "category": "ubisoft",
    "drm_type": "Ubisoft Connect",
    "notes": "Extract to game folder. Compatible with all versions."
  },
  {
    "appid": 201870,
    "name": "Assassin's Creed Revelations",
    "description": "Assassin's Creed Revelations DRM bypass",
    "download_url": "https://pixeldrain.com/api/file/YOUR_FILE_ID_HERE_3",
    "file_id": "YOUR_FILE_ID_HERE_3",
    "size": 10485760,
    "version": "1.0",
    "updated_at": "2025-01-15",
    "category": "ubisoft",
    "drm_type": "Ubisoft Connect",
    "notes": "Extract and run as administrator."
  },
  {
    "appid": 208480,
    "name": "Assassin's Creed III",
    "description": "AC III Ubisoft DRM removal tool",
    "download_url": "https://pixeldrain.com/api/file/YOUR_FILE_ID_HERE_4",
    "file_id": "YOUR_FILE_ID_HERE_4",
    "size": 18874368,
    "version": "1.0",
    "updated_at": "2025-01-15",
    "category": "ubisoft",
    "drm_type": "Ubisoft Connect",
    "notes": "Works with Steam version. May need DirectX."
  },
  {
    "appid": 242050,
    "name": "Assassin's Creed IV Black Flag",
    "description": "Black Flag bypass for offline play",
    "download_url": "https://pixeldrain.com/api/file/YOUR_FILE_ID_HERE_5",
    "file_id": "YOUR_FILE_ID_HERE_5",
    "size": 20971520,
    "version": "1.0",
    "updated_at": "2025-01-15",
    "category": "ubisoft",
    "drm_type": "Ubisoft Connect",
    "notes": "Install to game root directory."
  },
  {
    "appid": 368500,
    "name": "Assassin's Creed Syndicate",
    "description": "AC Syndicate Denuvo + Uplay bypass",
    "download_url": "https://pixeldrain.com/api/file/YOUR_FILE_ID_HERE_6",
    "file_id": "YOUR_FILE_ID_HERE_6",
    "size": 25165824,
    "version": "1.0",
    "updated_at": "2025-01-15",
    "category": "ubisoft",
    "drm_type": "Denuvo + Ubisoft Connect",
    "notes": "Denuvo removed. Extract all files to game folder."
  },
  {
    "appid": 812140,
    "name": "Assassin's Creed Odyssey",
    "description": "AC Odyssey DRM bypass tool",
    "download_url": "https://pixeldrain.com/api/file/YOUR_FILE_ID_HERE_7",
    "file_id": "YOUR_FILE_ID_HERE_7",
    "size": 31457280,
    "version": "1.0",
    "updated_at": "2025-01-15",
    "category": "ubisoft",
    "drm_type": "Ubisoft Connect + VMProtect",
    "notes": "Latest version. Supports all DLC."
  },
  {
    "appid": 271590,
    "name": "Grand Theft Auto V",
    "description": "GTA V Rockstar Social Club bypass",
    "download_url": "https://pixeldrain.com/api/file/YOUR_FILE_ID_HERE_8",
    "file_id": "YOUR_FILE_ID_HERE_8",
    "size": 41943040,
    "version": "1.0",
    "updated_at": "2025-01-15",
    "category": "rockstar",
    "drm_type": "Rockstar Social Club",
    "notes": "Offline mode enabled. Online features disabled."
  },
  {
    "appid": 1174180,
    "name": "Red Dead Redemption 2",
    "description": "RDR2 Rockstar launcher bypass",
    "download_url": "https://pixeldrain.com/api/file/YOUR_FILE_ID_HERE_9",
    "file_id": "YOUR_FILE_ID_HERE_9",
    "size": 52428800,
    "version": "1.0",
    "updated_at": "2025-01-15",
    "category": "rockstar",
    "drm_type": "Rockstar Social Club",
    "notes": "Extract to RDR2 root folder. Run as admin."
  },
  {
    "appid": 292030,
    "name": "The Witcher 3: Wild Hunt",
    "description": "Witcher 3 DRM-free version helper",
    "download_url": "https://pixeldrain.com/api/file/YOUR_FILE_ID_HERE_10",
    "file_id": "YOUR_FILE_ID_HERE_10",
    "size": 8388608,
    "version": "1.0",
    "updated_at": "2025-01-15",
    "category": "cd_projekt",
    "drm_type": "None (DRM-Free)",
    "notes": "Already DRM-free. This is optional optimization patch."
  }
]
